majorshare/__init__.py
majorshare/data_proxy.py
majorshare/http_client.py
majorshare/upass.py
majorshare-0.0.7.dist-info/LICENSE
majorshare-0.0.7.dist-info/METADATA
majorshare-0.0.7.dist-info/WHEEL
majorshare-0.0.7.dist-info/top_level.txt
majorshare-0.0.7.dist-info/RECORD
