Metadata-Version: 2.1
Name: majorshare
Version: 0.0.7
Summary: majorshare数据接口
Home-page: https://github.com/pypa/sampleproject
Author: majorshare author
Author-email: bhnw <888@gcolor7hua.site>
Classifier: Programming Language :: Python :: 3
Classifier: License :: OSI Approved :: GNU General Public License v3 (GPLv3)
Classifier: Operating System :: OS Independent
Requires-Python: >=3.6
License-File: LICENSE
Requires-Dist: majorshare
